<?xml version="1.0" encoding="utf-8"?>
<!DOCTYPE hibernate-mapping PUBLIC "-//Hibernate/Hibernate Mapping DTD 3.0//EN"
"http://hibernate.sourceforge.net/hibernate-mapping-3.0.dtd">
<!-- 
    Mapping file autogenerated by MyEclipse - Hibernate Tools
-->
<hibernate-mapping>
    <class name="com.kjnext.dmart.hibernate.UserDocuments" table="user_documents" >
        <id name="uidDocId" type="java.lang.Integer">
            <column name="uidDocId" />
            <generator class="increment" />
        </id>
        <many-to-one name="userDetail" class="com.kjnext.dmart.hibernate.UserDetail" fetch="select" lazy="false">
            <column name="userEmpId" not-null="true" />
        </many-to-one>
        <many-to-one name="documetRepository" class="com.kjnext.dmart.hibernate.DocumetRepository" fetch="select" lazy="false">
            <column name="docid" not-null="true" />
        </many-to-one>
        <property name="documentName" type="java.lang.String">
            <column name="documentName" length="45" not-null="true" />
        </property>
        <property name="createdDtm" type="java.util.Date">
            <column name="createdDTM" length="19" />
        </property>
        <property name="modifiedDtm" type="java.util.Date">
            <column name="modifiedDTM" length="19" />
        </property>
        <property name="createdUId" type="java.lang.Integer">
            <column name="created_uId" />
        </property>
        <property name="modifiedUId" type="java.lang.Integer">
            <column name="modified_uId" />
        </property>
    </class>
</hibernate-mapping>
